pandoc_run_python/__init__.py
pandoc_run_python/filter.py
pandoc_run_python/mpl_backend.py
pandoc_run_python/types.py
pandoc_run_python-0.1.25.dist-info/entry_points.txt
pandoc_run_python-0.1.25.dist-info/LICENSE
pandoc_run_python-0.1.25.dist-info/WHEEL
pandoc_run_python-0.1.25.dist-info/METADATA
pandoc_run_python-0.1.25.dist-info/RECORD
