Metadata-Version: 2.1
Name: pandoc-run-python
Version: 0.1.25
Summary: run python code blocks in markdown code
Home-page: https://github.com/Bart6114/pandoc-run-python
License: MIT
Author: Bart Smeets
Requires-Python: >=3.9,<4.0
Classifier: License :: OSI Approved :: MIT License
Classifier: Programming Language :: Python :: 3
Classifier: Programming Language :: Python :: 3.9
Classifier: Programming Language :: Python :: 3.10
Classifier: Programming Language :: Python :: 3.11
Provides-Extra: black
Requires-Dist: black (>=22.10.0,<23.0.0); extra == "black"
Requires-Dist: panflute (>=2.0.5,<3.0.0)
